glasswall/__init__.py
glasswall/utils.py
glasswall/config/__init__.py
glasswall/config/creationflags/__init__.py
glasswall/config/logging/__init__.py
glasswall/config/security_tagging/tags_w3schools.xml
glasswall/config/word_search/homoglyphs.json
glasswall/config/xml/__init__.py
glasswall/config/xml/xml.py
glasswall/content_management/__init__.py
glasswall/content_management/config_elements/__init__.py
glasswall/content_management/config_elements/archiveConfig.py
glasswall/content_management/config_elements/config_element.py
glasswall/content_management/config_elements/gifConfig.py
glasswall/content_management/config_elements/jpegConfig.py
glasswall/content_management/config_elements/pdfConfig.py
glasswall/content_management/config_elements/pptConfig.py
glasswall/content_management/config_elements/svgConfig.py
glasswall/content_management/config_elements/sysConfig.py
glasswall/content_management/config_elements/textList.py
glasswall/content_management/config_elements/textSearchConfig.py
glasswall/content_management/config_elements/tiffConfig.py
glasswall/content_management/config_elements/webpConfig.py
glasswall/content_management/config_elements/wordConfig.py
glasswall/content_management/config_elements/xlsConfig.py
glasswall/content_management/errors/__init__.py
glasswall/content_management/errors/config_elements.py
glasswall/content_management/errors/policies.py
glasswall/content_management/errors/switches.py
glasswall/content_management/policies/__init__.py
glasswall/content_management/policies/archive_manager.py
glasswall/content_management/policies/editor.py
glasswall/content_management/policies/policy.py
glasswall/content_management/policies/rebuild.py
glasswall/content_management/policies/word_search.py
glasswall/content_management/switches/__init__.py
glasswall/content_management/switches/archive.py
glasswall/content_management/switches/gif.py
glasswall/content_management/switches/jpeg.py
glasswall/content_management/switches/pdf.py
glasswall-5.9.0.dist-info/METADATA
glasswall-5.9.0.dist-info/WHEEL
glasswall-5.9.0.dist-info/top_level.txt
glasswall-5.9.0.dist-info/RECORD
