Metadata-Version: 2.4
Name: glasswall
Version: 5.9.0
Summary: Glasswall Python Wrapper
Author-email: AngusWR <aroberts@glasswall.com>
Project-URL: PyPI, https://pypi.org/project/glasswall
Classifier: Programming Language :: Python
Requires-Python: >=3.6
Requires-Dist: lxml<6,>=4.9.4
Requires-Dist: psutil<7,>=5.9.8
